country_list/__init__.py
country_list/__main__.py
country_list/country_list.py
country_list/country_data/data/af/country.csv
country_list/country_data/data/af_NA/country.csv
country_list/country_data/data/af_ZA/country.csv
country_list/country_data/data/ak/country.csv
country_list/country_data/data/ak_GH/country.csv
country_list/country_data/data/am/country.csv
country_list/country_data/data/am_ET/country.csv
country_list/country_data/data/ar/country.csv
country_list/country_data/data/ar_001/country.csv
country_list/country_data/data/ar_AE/country.csv
country_list/country_data/data/ar_BH/country.csv
country_list/country_data/data/ar_DJ/country.csv
country_list/country_data/data/ar_DZ/country.csv
country_list/country_data/data/ar_EG/country.csv
country_list/country_data/data/ar_EH/country.csv
country_list/country_data/data/ar_ER/country.csv
country_list/country_data/data/ar_IL/country.csv
country_list/country_data/data/ar_IQ/country.csv
country_list/country_data/data/ar_JO/country.csv
country_list/country_data/data/ar_KM/country.csv
country_list/country_data/data/ar_KW/country.csv
country_list/country_data/data/ar_LB/country.csv
country_list/country_data/data/ar_LY/country.csv
country_list/country_data/data/ar_MA/country.csv
country_list/country_data/data/ar_MR/country.csv
country_list/country_data/data/ar_OM/country.csv
country_list/country_data/data/ar_PS/country.csv
country_list/country_data/data/ar_QA/country.csv
country_list/country_data/data/ar_SA/country.csv
country_list/country_data/data/ar_SD/country.csv
country_list/country_data/data/ar_SO/country.csv
country_list/country_data/data/ar_SS/country.csv
country_list/country_data/data/ar_SY/country.csv
country_list/country_data/data/ar_TD/country.csv
country_list/country_data/data/ar_TN/country.csv
country_list/country_data/data/ar_YE/country.csv
country_list/country_data/data/as/country.csv
country_list/country_data/data/as_IN/country.csv
country_list/country_data/data/az/country.csv
country_list-1.0.0.dist-info/LICENSE
country_list-1.0.0.dist-info/METADATA
country_list-1.0.0.dist-info/WHEEL
country_list-1.0.0.dist-info/top_level.txt
country_list-1.0.0.dist-info/RECORD
