Metadata-Version: 1.1
Name: country_list
Version: 1.0.0
Summary: List of all countries with names and ISO 3166-1 codes in all languages
Home-page: https://github.com/bulv1ne/country_list
Author: Niels Lemmens
Author-email: draso.odin@gmail.com
License: MIT license
Keywords: country_list
Platform: UNKNOWN
Classifier: Development Status :: 4 - Beta
Classifier: Intended Audience :: Developers
Classifier: License :: OSI Approved :: MIT License
Classifier: Natural Language :: English
Classifier: Programming Language :: Python :: 3
Classifier: Programming Language :: Python :: 3.7
Classifier: Programming Language :: Python :: 3.8
Classifier: Programming Language :: Python :: 3.9
